{
  "generated_at": "2026-06-07 11:45",
  "market": "us",
  "period": "3m",
  "lookback": 63,
  "step": 5,
  "total_stocks": 952,
  "snapshots": [
    {
      "date": "2023-08-15",
      "bullish": 20.3,
      "bearish": 2.2,
      "sideways": 77,
      "recovering": 0.5,
      "netBreadth": 18.1,
      "total": 916
    },
    {
      "date": "2023-08-22",
      "bullish": 13.6,
      "bearish": 3.8,
      "sideways": 82.1,
      "recovering": 0.4,
      "netBreadth": 9.8,
      "total": 916
    },
    {
      "date": "2023-08-29",
      "bullish": 10.8,
      "bearish": 4.1,
      "sideways": 84.7,
      "recovering": 0.3,
      "netBreadth": 6.7,
      "total": 916
    },
    {
      "date": "2023-09-06",
      "bullish": 10,
      "bearish": 4.6,
      "sideways": 84.3,
      "recovering": 1.1,
      "netBreadth": 5.4,
      "total": 916
    },
    {
      "date": "2023-09-13",
      "bullish": 9.4,
      "bearish": 6.2,
      "sideways": 82.8,
      "recovering": 1.6,
      "netBreadth": 3.2,
      "total": 916
    },
    {
      "date": "2023-09-20",
      "bullish": 8.1,
      "bearish": 7.7,
      "sideways": 83.4,
      "recovering": 0.8,
      "netBreadth": 0.4,
      "total": 917
    },
    {
      "date": "2023-09-27",
      "bullish": 5.2,
      "bearish": 12.1,
      "sideways": 82.4,
      "recovering": 0.2,
      "netBreadth": -6.9,
      "total": 917
    },
    {
      "date": "2023-10-04",
      "bullish": 3.8,
      "bearish": 16.5,
      "sideways": 79.3,
      "recovering": 0.4,
      "netBreadth": -12.7,
      "total": 917
    },
    {
      "date": "2023-10-11",
      "bullish": 2.7,
      "bearish": 19.2,
      "sideways": 77.1,
      "recovering": 1,
      "netBreadth": -16.5,
      "total": 918
    },
    {
      "date": "2023-10-18",
      "bullish": 2.3,
      "bearish": 19.5,
      "sideways": 75.6,
      "recovering": 2.6,
      "netBreadth": -17.2,
      "total": 918
    },
    {
      "date": "2023-10-25",
      "bullish": 1.5,
      "bearish": 20.7,
      "sideways": 75.9,
      "recovering": 1.9,
      "netBreadth": -19.2,
      "total": 918
    },
    {
      "date": "2023-11-01",
      "bullish": 1.3,
      "bearish": 21.5,
      "sideways": 74.7,
      "recovering": 2.5,
      "netBreadth": -20.2,
      "total": 918
    },
    {
      "date": "2023-11-08",
      "bullish": 1.9,
      "bearish": 17.5,
      "sideways": 74.5,
      "recovering": 6.1,
      "netBreadth": -15.6,
      "total": 918
    },
    {
      "date": "2023-11-15",
      "bullish": 2.1,
      "bearish": 13,
      "sideways": 69.3,
      "recovering": 15.7,
      "netBreadth": -10.9,
      "total": 918
    },
    {
      "date": "2023-11-22",
      "bullish": 2.9,
      "bearish": 8,
      "sideways": 58.7,
      "recovering": 30.4,
      "netBreadth": -5.1,
      "total": 918
    },
    {
      "date": "2023-11-30",
      "bullish": 4,
      "bearish": 6.8,
      "sideways": 62.7,
      "recovering": 26.5,
      "netBreadth": -2.8,
      "total": 918
    },
    {
      "date": "2023-12-07",
      "bullish": 9.8,
      "bearish": 3.7,
      "sideways": 65.8,
      "recovering": 20.7,
      "netBreadth": 6.1,
      "total": 918
    },
    {
      "date": "2023-12-14",
      "bullish": 19.1,
      "bearish": 2.6,
      "sideways": 63.6,
      "recovering": 14.7,
      "netBreadth": 16.5,
      "total": 918
    },
    {
      "date": "2023-12-21",
      "bullish": 29.7,
      "bearish": 1.6,
      "sideways": 58.2,
      "recovering": 10.5,
      "netBreadth": 28.1,
      "total": 918
    },
    {
      "date": "2023-12-29",
      "bullish": 38.9,
      "bearish": 1.2,
      "sideways": 52.6,
      "recovering": 7.3,
      "netBreadth": 37.7,
      "total": 918
    },
    {
      "date": "2024-01-08",
      "bullish": 41.3,
      "bearish": 1.2,
      "sideways": 54.6,
      "recovering": 2.9,
      "netBreadth": 40.1,
      "total": 918
    },
    {
      "date": "2024-01-16",
      "bullish": 43.5,
      "bearish": 1.3,
      "sideways": 54.8,
      "recovering": 0.4,
      "netBreadth": 42.2,
      "total": 918
    },
    {
      "date": "2024-01-23",
      "bullish": 42.8,
      "bearish": 1.3,
      "sideways": 55.7,
      "recovering": 0.2,
      "netBreadth": 41.5,
      "total": 918
    },
    {
      "date": "2024-01-30",
      "bullish": 35.6,
      "bearish": 1.3,
      "sideways": 63,
      "recovering": 0.1,
      "netBreadth": 34.3,
      "total": 919
    },
    {
      "date": "2024-02-06",
      "bullish": 26.8,
      "bearish": 1.4,
      "sideways": 71.2,
      "recovering": 0.5,
      "netBreadth": 25.4,
      "total": 920
    },
    {
      "date": "2024-02-13",
      "bullish": 18.7,
      "bearish": 2.1,
      "sideways": 78.6,
      "recovering": 0.7,
      "netBreadth": 16.6,
      "total": 921
    },
    {
      "date": "2024-02-21",
      "bullish": 17.3,
      "bearish": 2.8,
      "sideways": 78.6,
      "recovering": 1.3,
      "netBreadth": 14.5,
      "total": 921
    },
    {
      "date": "2024-02-28",
      "bullish": 17,
      "bearish": 3.4,
      "sideways": 77.3,
      "recovering": 2.3,
      "netBreadth": 13.6,
      "total": 921
    },
    {
      "date": "2024-03-06",
      "bullish": 17,
      "bearish": 4.8,
      "sideways": 74.7,
      "recovering": 3.5,
      "netBreadth": 12.2,
      "total": 921
    },
    {
      "date": "2024-03-13",
      "bullish": 17.9,
      "bearish": 5.3,
      "sideways": 71.4,
      "recovering": 5.3,
      "netBreadth": 12.6,
      "total": 921
    },
    {
      "date": "2024-03-20",
      "bullish": 20.8,
      "bearish": 5.8,
      "sideways": 67.8,
      "recovering": 5.6,
      "netBreadth": 15,
      "total": 921
    },
    {
      "date": "2024-03-27",
      "bullish": 23.4,
      "bearish": 5.2,
      "sideways": 66.8,
      "recovering": 4.6,
      "netBreadth": 18.2,
      "total": 923
    },
    {
      "date": "2024-04-04",
      "bullish": 24.2,
      "bearish": 4.6,
      "sideways": 68,
      "recovering": 3.1,
      "netBreadth": 19.6,
      "total": 925
    },
    {
      "date": "2024-04-11",
      "bullish": 24.1,
      "bearish": 4.8,
      "sideways": 69,
      "recovering": 2.2,
      "netBreadth": 19.3,
      "total": 925
    },
    {
      "date": "2024-04-18",
      "bullish": 18.5,
      "bearish": 5.7,
      "sideways": 75.3,
      "recovering": 0.5,
      "netBreadth": 12.8,
      "total": 926
    },
    {
      "date": "2024-04-25",
      "bullish": 14.3,
      "bearish": 6.2,
      "sideways": 79,
      "recovering": 0.5,
      "netBreadth": 8.1,
      "total": 926
    },
    {
      "date": "2024-05-02",
      "bullish": 12.1,
      "bearish": 7.1,
      "sideways": 79.3,
      "recovering": 1.5,
      "netBreadth": 5,
      "total": 927
    },
    {
      "date": "2024-05-09",
      "bullish": 11.2,
      "bearish": 5.7,
      "sideways": 79.4,
      "recovering": 3.7,
      "netBreadth": 5.5,
      "total": 928
    },
    {
      "date": "2024-05-16",
      "bullish": 10.5,
      "bearish": 5.8,
      "sideways": 77.9,
      "recovering": 5.8,
      "netBreadth": 4.7,
      "total": 928
    },
    {
      "date": "2024-05-23",
      "bullish": 11.3,
      "bearish": 5.1,
      "sideways": 75.8,
      "recovering": 7.9,
      "netBreadth": 6.2,
      "total": 928
    },
    {
      "date": "2024-05-31",
      "bullish": 12,
      "bearish": 7,
      "sideways": 76.7,
      "recovering": 4.3,
      "netBreadth": 5,
      "total": 928
    },
    {
      "date": "2024-06-07",
      "bullish": 12.5,
      "bearish": 7.8,
      "sideways": 76.6,
      "recovering": 3.1,
      "netBreadth": 4.7,
      "total": 928
    },
    {
      "date": "2024-06-14",
      "bullish": 11.9,
      "bearish": 7.9,
      "sideways": 76.6,
      "recovering": 3.7,
      "netBreadth": 4,
      "total": 928
    },
    {
      "date": "2024-06-24",
      "bullish": 11.6,
      "bearish": 8.2,
      "sideways": 76.3,
      "recovering": 3.9,
      "netBreadth": 3.4,
      "total": 928
    },
    {
      "date": "2024-07-01",
      "bullish": 12,
      "bearish": 8.3,
      "sideways": 77.5,
      "recovering": 2.3,
      "netBreadth": 3.7,
      "total": 928
    },
    {
      "date": "2024-07-09",
      "bullish": 12.3,
      "bearish": 6.1,
      "sideways": 79.5,
      "recovering": 2,
      "netBreadth": 6.2,
      "total": 928
    },
    {
      "date": "2024-07-16",
      "bullish": 13,
      "bearish": 4,
      "sideways": 78.7,
      "recovering": 4.3,
      "netBreadth": 9,
      "total": 928
    },
    {
      "date": "2024-07-23",
      "bullish": 11,
      "bearish": 3.4,
      "sideways": 79.4,
      "recovering": 6.1,
      "netBreadth": 7.6,
      "total": 928
    },
    {
      "date": "2024-07-30",
      "bullish": 9.4,
      "bearish": 3.8,
      "sideways": 80.5,
      "recovering": 6.4,
      "netBreadth": 5.6,
      "total": 928
    },
    {
      "date": "2024-08-06",
      "bullish": 6.2,
      "bearish": 6.8,
      "sideways": 82.7,
      "recovering": 4.3,
      "netBreadth": -0.6,
      "total": 929
    },
    {
      "date": "2024-08-13",
      "bullish": 6.4,
      "bearish": 8.4,
      "sideways": 82.6,
      "recovering": 2.7,
      "netBreadth": -2,
      "total": 929
    },
    {
      "date": "2024-08-20",
      "bullish": 8.3,
      "bearish": 6.9,
      "sideways": 82,
      "recovering": 2.8,
      "netBreadth": 1.4,
      "total": 929
    },
    {
      "date": "2024-08-27",
      "bullish": 11.8,
      "bearish": 5.5,
      "sideways": 77.6,
      "recovering": 5.1,
      "netBreadth": 6.3,
      "total": 929
    },
    {
      "date": "2024-09-04",
      "bullish": 14.3,
      "bearish": 5.1,
      "sideways": 75,
      "recovering": 5.6,
      "netBreadth": 9.2,
      "total": 929
    },
    {
      "date": "2024-09-11",
      "bullish": 15.1,
      "bearish": 7.6,
      "sideways": 75.3,
      "recovering": 1.9,
      "netBreadth": 7.5,
      "total": 929
    },
    {
      "date": "2024-09-18",
      "bullish": 16.4,
      "bearish": 7.8,
      "sideways": 73.6,
      "recovering": 2.3,
      "netBreadth": 8.6,
      "total": 929
    },
    {
      "date": "2024-09-25",
      "bullish": 17.3,
      "bearish": 6.8,
      "sideways": 70.3,
      "recovering": 5.6,
      "netBreadth": 10.5,
      "total": 929
    },
    {
      "date": "2024-10-02",
      "bullish": 15.3,
      "bearish": 5,
      "sideways": 69.5,
      "recovering": 10.2,
      "netBreadth": 10.3,
      "total": 929
    },
    {
      "date": "2024-10-09",
      "bullish": 14,
      "bearish": 4.3,
      "sideways": 74.2,
      "recovering": 7.5,
      "netBreadth": 9.7,
      "total": 929
    },
    {
      "date": "2024-10-16",
      "bullish": 16.8,
      "bearish": 3,
      "sideways": 77.3,
      "recovering": 2.9,
      "netBreadth": 13.8,
      "total": 929
    },
    {
      "date": "2024-10-23",
      "bullish": 18.8,
      "bearish": 2.7,
      "sideways": 77.2,
      "recovering": 1.3,
      "netBreadth": 16.1,
      "total": 929
    },
    {
      "date": "2024-10-30",
      "bullish": 21.8,
      "bearish": 2.5,
      "sideways": 75.1,
      "recovering": 0.6,
      "netBreadth": 19.3,
      "total": 930
    },
    {
      "date": "2024-11-06",
      "bullish": 18.7,
      "bearish": 2.7,
      "sideways": 77.5,
      "recovering": 1.1,
      "netBreadth": 16,
      "total": 930
    },
    {
      "date": "2024-11-13",
      "bullish": 20.4,
      "bearish": 3.3,
      "sideways": 74.1,
      "recovering": 2.2,
      "netBreadth": 17.1,
      "total": 930
    },
    {
      "date": "2024-11-20",
      "bullish": 20.8,
      "bearish": 5.4,
      "sideways": 71.6,
      "recovering": 2.3,
      "netBreadth": 15.4,
      "total": 930
    },
    {
      "date": "2024-11-27",
      "bullish": 24,
      "bearish": 5.5,
      "sideways": 68.5,
      "recovering": 2,
      "netBreadth": 18.5,
      "total": 930
    },
    {
      "date": "2024-12-05",
      "bullish": 24.6,
      "bearish": 6.9,
      "sideways": 67.5,
      "recovering": 1,
      "netBreadth": 17.7,
      "total": 930
    },
    {
      "date": "2024-12-12",
      "bullish": 22.7,
      "bearish": 6.9,
      "sideways": 67.8,
      "recovering": 2.6,
      "netBreadth": 15.8,
      "total": 930
    },
    {
      "date": "2024-12-19",
      "bullish": 19.2,
      "bearish": 9.1,
      "sideways": 70.4,
      "recovering": 1.2,
      "netBreadth": 10.1,
      "total": 930
    },
    {
      "date": "2024-12-27",
      "bullish": 16.5,
      "bearish": 11.3,
      "sideways": 71.8,
      "recovering": 0.4,
      "netBreadth": 5.2,
      "total": 930
    },
    {
      "date": "2025-01-06",
      "bullish": 13,
      "bearish": 10.5,
      "sideways": 75.7,
      "recovering": 0.8,
      "netBreadth": 2.5,
      "total": 930
    },
    {
      "date": "2025-01-14",
      "bullish": 9.9,
      "bearish": 11.5,
      "sideways": 77.5,
      "recovering": 1.1,
      "netBreadth": -1.6,
      "total": 930
    },
    {
      "date": "2025-01-22",
      "bullish": 8.6,
      "bearish": 8.2,
      "sideways": 79,
      "recovering": 4.2,
      "netBreadth": 0.4,
      "total": 930
    },
    {
      "date": "2025-01-29",
      "bullish": 7.2,
      "bearish": 6.3,
      "sideways": 78,
      "recovering": 8.5,
      "netBreadth": 0.9,
      "total": 930
    },
    {
      "date": "2025-02-05",
      "bullish": 6.9,
      "bearish": 5.8,
      "sideways": 78.3,
      "recovering": 9,
      "netBreadth": 1.1,
      "total": 932
    },
    {
      "date": "2025-02-12",
      "bullish": 7.2,
      "bearish": 6,
      "sideways": 79.5,
      "recovering": 7.3,
      "netBreadth": 1.2,
      "total": 932
    },
    {
      "date": "2025-02-20",
      "bullish": 8.7,
      "bearish": 6.3,
      "sideways": 76.8,
      "recovering": 8.1,
      "netBreadth": 2.4,
      "total": 933
    },
    {
      "date": "2025-02-27",
      "bullish": 7.8,
      "bearish": 7.9,
      "sideways": 78.6,
      "recovering": 5.7,
      "netBreadth": -0.1,
      "total": 933
    },
    {
      "date": "2025-03-06",
      "bullish": 8.7,
      "bearish": 8.9,
      "sideways": 78.8,
      "recovering": 3.6,
      "netBreadth": -0.2,
      "total": 933
    },
    {
      "date": "2025-03-13",
      "bullish": 8.6,
      "bearish": 10.2,
      "sideways": 79.5,
      "recovering": 1.7,
      "netBreadth": -1.6,
      "total": 933
    },
    {
      "date": "2025-03-20",
      "bullish": 10.4,
      "bearish": 11.8,
      "sideways": 76.7,
      "recovering": 1.1,
      "netBreadth": -1.4,
      "total": 933
    },
    {
      "date": "2025-03-27",
      "bullish": 10.1,
      "bearish": 12.4,
      "sideways": 74.8,
      "recovering": 2.7,
      "netBreadth": -2.3,
      "total": 933
    },
    {
      "date": "2025-04-03",
      "bullish": 9.1,
      "bearish": 16.4,
      "sideways": 71,
      "recovering": 3.5,
      "netBreadth": -7.3,
      "total": 934
    },
    {
      "date": "2025-04-10",
      "bullish": 5,
      "bearish": 30.2,
      "sideways": 64.5,
      "recovering": 0.3,
      "netBreadth": -25.2,
      "total": 934
    },
    {
      "date": "2025-04-17",
      "bullish": 3.4,
      "bearish": 38.8,
      "sideways": 56.9,
      "recovering": 1,
      "netBreadth": -35.4,
      "total": 934
    },
    {
      "date": "2025-04-25",
      "bullish": 3,
      "bearish": 37,
      "sideways": 55.4,
      "recovering": 4.6,
      "netBreadth": -34,
      "total": 934
    },
    {
      "date": "2025-05-02",
      "bullish": 3.5,
      "bearish": 13.5,
      "sideways": 50.9,
      "recovering": 32.1,
      "netBreadth": -10,
      "total": 934
    },
    {
      "date": "2025-05-09",
      "bullish": 3.6,
      "bearish": 10.1,
      "sideways": 46.8,
      "recovering": 39.5,
      "netBreadth": -6.5,
      "total": 934
    },
    {
      "date": "2025-05-16",
      "bullish": 4.9,
      "bearish": 6.1,
      "sideways": 44.4,
      "recovering": 44.5,
      "netBreadth": -1.2,
      "total": 934
    },
    {
      "date": "2025-05-23",
      "bullish": 8.6,
      "bearish": 7.2,
      "sideways": 51.9,
      "recovering": 32.3,
      "netBreadth": 1.4,
      "total": 934
    },
    {
      "date": "2025-06-02",
      "bullish": 13.8,
      "bearish": 6.1,
      "sideways": 67.8,
      "recovering": 12.3,
      "netBreadth": 7.7,
      "total": 934
    },
    {
      "date": "2025-06-09",
      "bullish": 20.1,
      "bearish": 4.7,
      "sideways": 70.7,
      "recovering": 4.5,
      "netBreadth": 15.4,
      "total": 934
    },
    {
      "date": "2025-06-16",
      "bullish": 24.7,
      "bearish": 3.2,
      "sideways": 68.2,
      "recovering": 4,
      "netBreadth": 21.5,
      "total": 936
    },
    {
      "date": "2025-06-24",
      "bullish": 32,
      "bearish": 2.3,
      "sideways": 62.5,
      "recovering": 3.1,
      "netBreadth": 29.7,
      "total": 937
    },
    {
      "date": "2025-07-01",
      "bullish": 38.3,
      "bearish": 1.7,
      "sideways": 59.1,
      "recovering": 1,
      "netBreadth": 36.6,
      "total": 938
    },
    {
      "date": "2025-07-09",
      "bullish": 39.2,
      "bearish": 1.6,
      "sideways": 58.3,
      "recovering": 0.9,
      "netBreadth": 37.6,
      "total": 938
    },
    {
      "date": "2025-07-16",
      "bullish": 34.8,
      "bearish": 1.3,
      "sideways": 62.4,
      "recovering": 1.6,
      "netBreadth": 33.5,
      "total": 938
    },
    {
      "date": "2025-07-23",
      "bullish": 29.4,
      "bearish": 1.4,
      "sideways": 67.4,
      "recovering": 1.8,
      "netBreadth": 28,
      "total": 938
    },
    {
      "date": "2025-07-30",
      "bullish": 26.7,
      "bearish": 1.6,
      "sideways": 70.3,
      "recovering": 1.5,
      "netBreadth": 25.1,
      "total": 938
    },
    {
      "date": "2025-08-06",
      "bullish": 22.4,
      "bearish": 2.2,
      "sideways": 74.3,
      "recovering": 1.1,
      "netBreadth": 20.2,
      "total": 939
    },
    {
      "date": "2025-08-13",
      "bullish": 21.7,
      "bearish": 3.2,
      "sideways": 73.9,
      "recovering": 1.2,
      "netBreadth": 18.5,
      "total": 939
    },
    {
      "date": "2025-08-20",
      "bullish": 22.6,
      "bearish": 3.4,
      "sideways": 72.3,
      "recovering": 1.7,
      "netBreadth": 19.2,
      "total": 939
    },
    {
      "date": "2025-08-27",
      "bullish": 22,
      "bearish": 3.3,
      "sideways": 72.5,
      "recovering": 2.1,
      "netBreadth": 18.7,
      "total": 939
    },
    {
      "date": "2025-09-04",
      "bullish": 21.4,
      "bearish": 3.7,
      "sideways": 72.6,
      "recovering": 2.2,
      "netBreadth": 17.7,
      "total": 939
    },
    {
      "date": "2025-09-11",
      "bullish": 21.7,
      "bearish": 4.5,
      "sideways": 71.4,
      "recovering": 2.4,
      "netBreadth": 17.2,
      "total": 939
    },
    {
      "date": "2025-09-18",
      "bullish": 20.9,
      "bearish": 5.1,
      "sideways": 71,
      "recovering": 3,
      "netBreadth": 15.8,
      "total": 939
    },
    {
      "date": "2025-09-25",
      "bullish": 20.4,
      "bearish": 4.8,
      "sideways": 71.1,
      "recovering": 3.6,
      "netBreadth": 15.6,
      "total": 939
    },
    {
      "date": "2025-10-02",
      "bullish": 19.7,
      "bearish": 4.8,
      "sideways": 72.3,
      "recovering": 3.2,
      "netBreadth": 14.9,
      "total": 939
    },
    {
      "date": "2025-10-09",
      "bullish": 19,
      "bearish": 4.3,
      "sideways": 73.3,
      "recovering": 3.5,
      "netBreadth": 14.7,
      "total": 939
    },
    {
      "date": "2025-10-16",
      "bullish": 18,
      "bearish": 4.2,
      "sideways": 75.8,
      "recovering": 2,
      "netBreadth": 13.8,
      "total": 939
    },
    {
      "date": "2025-10-23",
      "bullish": 17,
      "bearish": 3.5,
      "sideways": 78.1,
      "recovering": 1.4,
      "netBreadth": 13.5,
      "total": 939
    },
    {
      "date": "2025-10-30",
      "bullish": 17.3,
      "bearish": 3.2,
      "sideways": 78.1,
      "recovering": 1.4,
      "netBreadth": 14.1,
      "total": 940
    },
    {
      "date": "2025-11-06",
      "bullish": 17.3,
      "bearish": 5.2,
      "sideways": 76.3,
      "recovering": 1.2,
      "netBreadth": 12.1,
      "total": 941
    },
    {
      "date": "2025-11-13",
      "bullish": 17.2,
      "bearish": 7.8,
      "sideways": 73.3,
      "recovering": 1.7,
      "netBreadth": 9.4,
      "total": 941
    },
    {
      "date": "2025-11-20",
      "bullish": 14.6,
      "bearish": 9.5,
      "sideways": 74.9,
      "recovering": 1.1,
      "netBreadth": 5.1,
      "total": 941
    },
    {
      "date": "2025-11-28",
      "bullish": 13.7,
      "bearish": 10.1,
      "sideways": 74,
      "recovering": 2.2,
      "netBreadth": 3.6,
      "total": 941
    },
    {
      "date": "2025-12-05",
      "bullish": 13.4,
      "bearish": 9.2,
      "sideways": 72.8,
      "recovering": 4.6,
      "netBreadth": 4.2,
      "total": 941
    },
    {
      "date": "2025-12-12",
      "bullish": 14,
      "bearish": 6.9,
      "sideways": 69.9,
      "recovering": 9.1,
      "netBreadth": 7.1,
      "total": 941
    },
    {
      "date": "2025-12-19",
      "bullish": 13.6,
      "bearish": 7.3,
      "sideways": 70,
      "recovering": 9,
      "netBreadth": 6.3,
      "total": 941
    },
    {
      "date": "2025-12-29",
      "bullish": 14.9,
      "bearish": 8.4,
      "sideways": 71.3,
      "recovering": 5.4,
      "netBreadth": 6.5,
      "total": 942
    },
    {
      "date": "2026-01-06",
      "bullish": 17.9,
      "bearish": 7.4,
      "sideways": 71.2,
      "recovering": 3.5,
      "netBreadth": 10.5,
      "total": 943
    },
    {
      "date": "2026-01-13",
      "bullish": 19.1,
      "bearish": 5,
      "sideways": 70.2,
      "recovering": 5.7,
      "netBreadth": 14.1,
      "total": 943
    },
    {
      "date": "2026-01-21",
      "bullish": 20.5,
      "bearish": 5,
      "sideways": 69.2,
      "recovering": 5.3,
      "netBreadth": 15.5,
      "total": 943
    },
    {
      "date": "2026-01-28",
      "bullish": 22.8,
      "bearish": 5.2,
      "sideways": 67.1,
      "recovering": 4.9,
      "netBreadth": 17.6,
      "total": 943
    },
    {
      "date": "2026-02-04",
      "bullish": 24.3,
      "bearish": 5.9,
      "sideways": 66.4,
      "recovering": 3.4,
      "netBreadth": 18.4,
      "total": 943
    },
    {
      "date": "2026-02-11",
      "bullish": 28.5,
      "bearish": 6,
      "sideways": 62.3,
      "recovering": 3.2,
      "netBreadth": 22.5,
      "total": 944
    },
    {
      "date": "2026-02-19",
      "bullish": 31.1,
      "bearish": 7.8,
      "sideways": 58.5,
      "recovering": 2.5,
      "netBreadth": 23.3,
      "total": 944
    },
    {
      "date": "2026-02-26",
      "bullish": 31.8,
      "bearish": 10.8,
      "sideways": 55,
      "recovering": 2.4,
      "netBreadth": 21,
      "total": 944
    },
    {
      "date": "2026-03-05",
      "bullish": 30.2,
      "bearish": 10.2,
      "sideways": 56.6,
      "recovering": 3.1,
      "netBreadth": 20,
      "total": 944
    },
    {
      "date": "2026-03-12",
      "bullish": 26.6,
      "bearish": 10.4,
      "sideways": 58.4,
      "recovering": 4.7,
      "netBreadth": 16.2,
      "total": 945
    },
    {
      "date": "2026-03-19",
      "bullish": 22.4,
      "bearish": 13.5,
      "sideways": 60.3,
      "recovering": 3.8,
      "netBreadth": 8.9,
      "total": 946
    },
    {
      "date": "2026-03-26",
      "bullish": 17.1,
      "bearish": 18.6,
      "sideways": 63.2,
      "recovering": 1.1,
      "netBreadth": -1.5,
      "total": 946
    },
    {
      "date": "2026-04-02",
      "bullish": 13.6,
      "bearish": 22.2,
      "sideways": 63.4,
      "recovering": 0.7,
      "netBreadth": -8.6,
      "total": 946
    },
    {
      "date": "2026-04-10",
      "bullish": 11.9,
      "bearish": 20.9,
      "sideways": 61.4,
      "recovering": 5.7,
      "netBreadth": -9,
      "total": 946
    },
    {
      "date": "2026-04-17",
      "bullish": 11,
      "bearish": 10.3,
      "sideways": 57.8,
      "recovering": 20.9,
      "netBreadth": 0.7,
      "total": 946
    },
    {
      "date": "2026-04-24",
      "bullish": 11.2,
      "bearish": 7.4,
      "sideways": 55.4,
      "recovering": 26.1,
      "netBreadth": 3.8,
      "total": 948
    },
    {
      "date": "2026-05-01",
      "bullish": 11.6,
      "bearish": 10.1,
      "sideways": 63.3,
      "recovering": 15,
      "netBreadth": 1.5,
      "total": 948
    },
    {
      "date": "2026-05-08",
      "bullish": 12.9,
      "bearish": 10.1,
      "sideways": 67.2,
      "recovering": 9.8,
      "netBreadth": 2.8,
      "total": 949
    },
    {
      "date": "2026-05-15",
      "bullish": 16.4,
      "bearish": 9.5,
      "sideways": 68,
      "recovering": 6.1,
      "netBreadth": 6.9,
      "total": 950
    },
    {
      "date": "2026-05-22",
      "bullish": 18.3,
      "bearish": 8.7,
      "sideways": 69.6,
      "recovering": 3.4,
      "netBreadth": 9.6,
      "total": 952
    },
    {
      "date": "2026-06-01",
      "bullish": 22.9,
      "bearish": 7.2,
      "sideways": 66.1,
      "recovering": 3.8,
      "netBreadth": 15.7,
      "total": 952
    }
  ]
}