{
  "generated_at": "2026-06-07 11:45",
  "period": "1y",
  "analyzed_count": 199,
  "skipped_count": 1,
  "summary": {
    "bullish": 130,
    "bearish": 15,
    "sideways": 42,
    "recovering": 12
  },
  "stocks": [
    {
      "ticker": "005930.KS",
      "trend": "bullish",
      "slopePct": 14.03,
      "r2": 0.871,
      "slopeEarlyPct": 13.098,
      "slopeLatePct": 14.99,
      "totalReturn": 450.2
    },
    {
      "ticker": "000660.KS",
      "trend": "bullish",
      "slopePct": 17.434,
      "r2": 0.789,
      "slopeEarlyPct": 17.902,
      "slopeLatePct": 23.448,
      "totalReturn": 608.9
    },
    {
      "ticker": "005935.KS",
      "trend": "bullish",
      "slopePct": 12.046,
      "r2": 0.888,
      "slopeEarlyPct": 11.288,
      "slopeLatePct": 13.434,
      "totalReturn": 326.3
    },
    {
      "ticker": "005380.KS",
      "trend": "bullish",
      "slopePct": 11.475,
      "r2": 0.821,
      "slopeEarlyPct": 11.658,
      "slopeLatePct": 5.36,
      "totalReturn": 244
    },
    {
      "ticker": "402340.KS",
      "trend": "bullish",
      "slopePct": 17.746,
      "r2": 0.825,
      "slopeEarlyPct": 18.746,
      "slopeLatePct": 22.42,
      "totalReturn": 587.4
    },
    {
      "ticker": "009150.KS",
      "trend": "bullish",
      "slopePct": 23.076,
      "r2": 0.6,
      "slopeEarlyPct": 10.65,
      "slopeLatePct": 38.913,
      "totalReturn": 1204.4
    },
    {
      "ticker": "373220.KS",
      "trend": "bullish",
      "slopePct": 2.141,
      "r2": 0.437,
      "slopeEarlyPct": 2.928,
      "slopeLatePct": 0.87,
      "totalReturn": 39.4
    },
    {
      "ticker": "028260.KS",
      "trend": "bullish",
      "slopePct": 8.583,
      "r2": 0.825,
      "slopeEarlyPct": 8.809,
      "slopeLatePct": 11.111,
      "totalReturn": 185.3
    },
    {
      "ticker": "032830.KS",
      "trend": "bullish",
      "slopePct": 10.058,
      "r2": 0.751,
      "slopeEarlyPct": 4.832,
      "slopeLatePct": 18.209,
      "totalReturn": 223.8
    },
    {
      "ticker": "329180.KS",
      "trend": "bullish",
      "slopePct": 2.938,
      "r2": 0.57,
      "slopeEarlyPct": 2.848,
      "slopeLatePct": 5.67,
      "totalReturn": 55
    },
    {
      "ticker": "005387.KS",
      "trend": "bullish",
      "slopePct": 4.772,
      "r2": 0.657,
      "slopeEarlyPct": 7.019,
      "slopeLatePct": -3.275,
      "totalReturn": 63.6
    },
    {
      "ticker": "005385.KS",
      "trend": "bullish",
      "slopePct": 5.013,
      "r2": 0.677,
      "slopeEarlyPct": 7.077,
      "slopeLatePct": -3.002,
      "totalReturn": 67.6
    },
    {
      "ticker": "000270.KS",
      "trend": "bullish",
      "slopePct": 5.098,
      "r2": 0.662,
      "slopeEarlyPct": 5.538,
      "slopeLatePct": -3.89,
      "totalReturn": 66.3
    },
    {
      "ticker": "012330.KS",
      "trend": "bullish",
      "slopePct": 7.935,
      "r2": 0.681,
      "slopeEarlyPct": 5.46,
      "slopeLatePct": 13.465,
      "totalReturn": 142.9
    },
    {
      "ticker": "207940.KS",
      "trend": "sideways",
      "slopePct": -1.013,
      "r2": 0.156,
      "slopeEarlyPct": 1.707,
      "slopeLatePct": -6.821,
      "totalReturn": -12.1
    },
    {
      "ticker": "034020.KS",
      "trend": "bullish",
      "slopePct": 4.875,
      "r2": 0.677,
      "slopeEarlyPct": 4.427,
      "slopeLatePct": -0.722,
      "totalReturn": 39.8
    },
    {
      "ticker": "105560.KS",
      "trend": "bullish",
      "slopePct": 3.906,
      "r2": 0.876,
      "slopeEarlyPct": 2.917,
      "slopeLatePct": 2.163,
      "totalReturn": 54.7
    },
    {
      "ticker": "066570.KS",
      "trend": "bullish",
      "slopePct": 12.707,
      "r2": 0.629,
      "slopeEarlyPct": 4.25,
      "slopeLatePct": 25.4,
      "totalReturn": 310.6
    },
    {
      "ticker": "012450.KS",
      "trend": "bullish",
      "slopePct": 2.823,
      "r2": 0.426,
      "slopeEarlyPct": 3.21,
      "slopeLatePct": -3.025,
      "totalReturn": 23.7
    },
    {
      "ticker": "055550.KS",
      "trend": "bullish",
      "slopePct": 4.346,
      "r2": 0.918,
      "slopeEarlyPct": 4.043,
      "slopeLatePct": 2.79,
      "totalReturn": 75.1
    },
    {
      "ticker": "009155.KS",
      "trend": "bullish",
      "slopePct": 20.924,
      "r2": 0.622,
      "slopeEarlyPct": 10.465,
      "slopeLatePct": 34.647,
      "totalReturn": 888.4
    },
    {
      "ticker": "006400.KS",
      "trend": "bullish",
      "slopePct": 11.31,
      "r2": 0.834,
      "slopeEarlyPct": 10.402,
      "slopeLatePct": 8.566,
      "totalReturn": 228.7
    },
    {
      "ticker": "068270.KS",
      "trend": "sideways",
      "slopePct": 1.596,
      "r2": 0.321,
      "slopeEarlyPct": 2.791,
      "slopeLatePct": -6.013,
      "totalReturn": 12.8
    },
    {
      "ticker": "035420.KS",
      "trend": "sideways",
      "slopePct": -0.58,
      "r2": 0.055,
      "slopeEarlyPct": 1.007,
      "slopeLatePct": 1.492,
      "totalReturn": -2.7
    },
    {
      "ticker": "267260.KS",
      "trend": "bullish",
      "slopePct": 6.589,
      "r2": 0.756,
      "slopeEarlyPct": 9.142,
      "slopeLatePct": 0.321,
      "totalReturn": 88.6
    },
    {
      "ticker": "042660.KS",
      "trend": "sideways",
      "slopePct": 1.849,
      "r2": 0.262,
      "slopeEarlyPct": 4.544,
      "slopeLatePct": -4.366,
      "totalReturn": 41.3
    },
    {
      "ticker": "034730.KS",
      "trend": "bullish",
      "slopePct": 10.503,
      "r2": 0.754,
      "slopeEarlyPct": 6.837,
      "slopeLatePct": 16.948,
      "totalReturn": 205.6
    },
    {
      "ticker": "010120.KS",
      "trend": "bullish",
      "slopePct": 13.737,
      "r2": 0.808,
      "slopeEarlyPct": 10.12,
      "slopeLatePct": 11.317,
      "totalReturn": 279.6
    },
    {
      "ticker": "086790.KS",
      "trend": "bullish",
      "slopePct": 3.78,
      "r2": 0.812,
      "slopeEarlyPct": 2.29,
      "slopeLatePct": 1.017,
      "totalReturn": 43.2
    },
    {
      "ticker": "006800.KS",
      "trend": "bullish",
      "slopePct": 11.757,
      "r2": 0.744,
      "slopeEarlyPct": 8.946,
      "slopeLatePct": -4.808,
      "totalReturn": 164.9
    },
    {
      "ticker": "298040.KS",
      "trend": "bullish",
      "slopePct": 10.54,
      "r2": 0.883,
      "slopeEarlyPct": 12.733,
      "slopeLatePct": 7.207,
      "totalReturn": 279.3
    },
    {
      "ticker": "000150.KS",
      "trend": "bullish",
      "slopePct": 10.422,
      "r2": 0.786,
      "slopeEarlyPct": 5.93,
      "slopeLatePct": 12.283,
      "totalReturn": 165.2
    },
    {
      "ticker": "000810.KS",
      "trend": "bullish",
      "slopePct": 2.729,
      "r2": 0.504,
      "slopeEarlyPct": 2.204,
      "slopeLatePct": 8.505,
      "totalReturn": 60.1
    },
    {
      "ticker": "005490.KS",
      "trend": "bullish",
      "slopePct": 3.984,
      "r2": 0.71,
      "slopeEarlyPct": 2.752,
      "slopeLatePct": 1.113,
      "totalReturn": 49.4
    },
    {
      "ticker": "011070.KS",
      "trend": "bullish",
      "slopePct": 19.21,
      "r2": 0.577,
      "slopeEarlyPct": 8.705,
      "slopeLatePct": 37.419,
      "totalReturn": 687
    },
    {
      "ticker": "051910.KS",
      "trend": "bullish",
      "slopePct": 2.766,
      "r2": 0.365,
      "slopeEarlyPct": 4.83,
      "slopeLatePct": -1.886,
      "totalReturn": 65
    },
    {
      "ticker": "042700.KS",
      "trend": "bullish",
      "slopePct": 11.675,
      "r2": 0.772,
      "slopeEarlyPct": 10.632,
      "slopeLatePct": -1.658,
      "totalReturn": 177.5
    },
    {
      "ticker": "009540.KS",
      "trend": "sideways",
      "slopePct": 0.502,
      "r2": 0.042,
      "slopeEarlyPct": 1.895,
      "slopeLatePct": -1.531,
      "totalReturn": 3.6
    },
    {
      "ticker": "015760.KS",
      "trend": "sideways",
      "slopePct": 0.973,
      "r2": 0.045,
      "slopeEarlyPct": 6.277,
      "slopeLatePct": -9.866,
      "totalReturn": -3.1
    },
    {
      "ticker": "010140.KS",
      "trend": "bullish",
      "slopePct": 3.613,
      "r2": 0.597,
      "slopeEarlyPct": 6.717,
      "slopeLatePct": 0.389,
      "totalReturn": 65.6
    },
    {
      "ticker": "010130.KS",
      "trend": "bullish",
      "slopePct": 5.425,
      "r2": 0.461,
      "slopeEarlyPct": 12.48,
      "slopeLatePct": -10.295,
      "totalReturn": 54.5
    },
    {
      "ticker": "307950.KS",
      "trend": "bullish",
      "slopePct": 15.141,
      "r2": 0.758,
      "slopeEarlyPct": 15.714,
      "slopeLatePct": 20.19,
      "totalReturn": 390
    },
    {
      "ticker": "316140.KS",
      "trend": "bullish",
      "slopePct": 2.987,
      "r2": 0.697,
      "slopeEarlyPct": 3.469,
      "slopeLatePct": -3.681,
      "totalReturn": 39
    },
    {
      "ticker": "017670.KS",
      "trend": "bullish",
      "slopePct": 6.463,
      "r2": 0.785,
      "slopeEarlyPct": 1.965,
      "slopeLatePct": 8.444,
      "totalReturn": 87.7
    },
    {
      "ticker": "064350.KS",
      "trend": "sideways",
      "slopePct": 0.461,
      "r2": 0.018,
      "slopeEarlyPct": 0.756,
      "slopeLatePct": -2.226,
      "totalReturn": -2.6
    },
    {
      "ticker": "096770.KS",
      "trend": "sideways",
      "slopePct": 1.005,
      "r2": 0.118,
      "slopeEarlyPct": -0.381,
      "slopeLatePct": -1.224,
      "totalReturn": -6.1
    },
    {
      "ticker": "018260.KS",
      "trend": "bullish",
      "slopePct": 3.738,
      "r2": 0.384,
      "slopeEarlyPct": 1.182,
      "slopeLatePct": 12.415,
      "totalReturn": 48.9
    },
    {
      "ticker": "267250.KS",
      "trend": "bullish",
      "slopePct": 6.896,
      "r2": 0.852,
      "slopeEarlyPct": 8.153,
      "slopeLatePct": -0.126,
      "totalReturn": 109.7
    },
    {
      "ticker": "003550.KS",
      "trend": "bullish",
      "slopePct": 4.75,
      "r2": 0.601,
      "slopeEarlyPct": 1.696,
      "slopeLatePct": 8.424,
      "totalReturn": 54.4
    },
    {
      "ticker": "033780.KS",
      "trend": "bullish",
      "slopePct": 3.257,
      "r2": 0.918,
      "slopeEarlyPct": 2.362,
      "slopeLatePct": 3.348,
      "totalReturn": 40.4
    },
    {
      "ticker": "003670.KS",
      "trend": "bullish",
      "slopePct": 4.805,
      "r2": 0.693,
      "slopeEarlyPct": 8.038,
      "slopeLatePct": -1.469,
      "totalReturn": 65.3
    },
    {
      "ticker": "011200.KS",
      "trend": "bearish",
      "slopePct": -1.146,
      "r2": 0.492,
      "slopeEarlyPct": -2.299,
      "slopeLatePct": -1.897,
      "totalReturn": -13.6
    },
    {
      "ticker": "035720.KS",
      "trend": "bearish",
      "slopePct": -3.002,
      "r2": 0.58,
      "slopeEarlyPct": 0.283,
      "slopeLatePct": -10.09,
      "totalReturn": -32.9
    },
    {
      "ticker": "138040.KS",
      "trend": "sideways",
      "slopePct": -0.58,
      "r2": 0.141,
      "slopeEarlyPct": -0.431,
      "slopeLatePct": -4.292,
      "totalReturn": -4.6
    },
    {
      "ticker": "272210.KS",
      "trend": "bullish",
      "slopePct": 7.18,
      "r2": 0.644,
      "slopeEarlyPct": 4.238,
      "slopeLatePct": -4.324,
      "totalReturn": 63.1
    },
    {
      "ticker": "000815.KS",
      "trend": "bullish",
      "slopePct": 1.603,
      "r2": 0.625,
      "slopeEarlyPct": 2.412,
      "slopeLatePct": 0.17,
      "totalReturn": 26.5
    },
    {
      "ticker": "066575.KS",
      "trend": "bullish",
      "slopePct": 8.322,
      "r2": 0.719,
      "slopeEarlyPct": 5.133,
      "slopeLatePct": 14.827,
      "totalReturn": 165.5
    },
    {
      "ticker": "024110.KS",
      "trend": "sideways",
      "slopePct": 1.395,
      "r2": 0.333,
      "slopeEarlyPct": 2.354,
      "slopeLatePct": -5.133,
      "totalReturn": 13.1
    },
    {
      "ticker": "079550.KS",
      "trend": "recovering",
      "slopePct": 3.928,
      "r2": 0.316,
      "slopeEarlyPct": -4.212,
      "slopeLatePct": 8.696,
      "totalReturn": 34.4
    },
    {
      "ticker": "086280.KS",
      "trend": "bullish",
      "slopePct": 4.144,
      "r2": 0.545,
      "slopeEarlyPct": 5.948,
      "slopeLatePct": -5.315,
      "totalReturn": 55.4
    },
    {
      "ticker": "000720.KS",
      "trend": "bullish",
      "slopePct": 8.681,
      "r2": 0.677,
      "slopeEarlyPct": 3.532,
      "slopeLatePct": -4.06,
      "totalReturn": 68
    },
    {
      "ticker": "278470.KS",
      "trend": "bullish",
      "slopePct": 7.072,
      "r2": 0.883,
      "slopeEarlyPct": 5.932,
      "slopeLatePct": 5.69,
      "totalReturn": 152.3
    },
    {
      "ticker": "071050.KS",
      "trend": "bullish",
      "slopePct": 5.549,
      "r2": 0.806,
      "slopeEarlyPct": 5.499,
      "slopeLatePct": 0.464,
      "totalReturn": 76.6
    },
    {
      "ticker": "047810.KS",
      "trend": "bullish",
      "slopePct": 5.686,
      "r2": 0.663,
      "slopeEarlyPct": 7.398,
      "slopeLatePct": -6.09,
      "totalReturn": 54.8
    },
    {
      "ticker": "010950.KS",
      "trend": "bullish",
      "slopePct": 6.643,
      "r2": 0.84,
      "slopeEarlyPct": 7.88,
      "slopeLatePct": 0.675,
      "totalReturn": 88.3
    },
    {
      "ticker": "030200.KS",
      "trend": "sideways",
      "slopePct": 0.703,
      "r2": 0.117,
      "slopeEarlyPct": -0.382,
      "slopeLatePct": -4.659,
      "totalReturn": -3.1
    },
    {
      "ticker": "051915.KS",
      "trend": "sideways",
      "slopePct": 1.97,
      "r2": 0.208,
      "slopeEarlyPct": 5.045,
      "slopeLatePct": -3.931,
      "totalReturn": 47
    },
    {
      "ticker": "005940.KS",
      "trend": "bullish",
      "slopePct": 5.314,
      "r2": 0.734,
      "slopeEarlyPct": 3.313,
      "slopeLatePct": -2.147,
      "totalReturn": 58.8
    },
    {
      "ticker": "259960.KS",
      "trend": "recovering",
      "slopePct": -2.774,
      "r2": 0.647,
      "slopeEarlyPct": -5.694,
      "slopeLatePct": 0.799,
      "totalReturn": -29.1
    },
    {
      "ticker": "006260.KS",
      "trend": "bullish",
      "slopePct": 8.901,
      "r2": 0.719,
      "slopeEarlyPct": 2.505,
      "slopeLatePct": 11.946,
      "totalReturn": 108.4
    },
    {
      "ticker": "064400.KS",
      "trend": "recovering",
      "slopePct": 3.406,
      "r2": 0.256,
      "slopeEarlyPct": -1.99,
      "slopeLatePct": 16.878,
      "totalReturn": 56.5
    },
    {
      "ticker": "000880.KS",
      "trend": "bullish",
      "slopePct": 3.851,
      "r2": 0.552,
      "slopeEarlyPct": 0.626,
      "slopeLatePct": 0.314,
      "totalReturn": 32.9
    },
    {
      "ticker": "016360.KS",
      "trend": "bullish",
      "slopePct": 5.134,
      "r2": 0.843,
      "slopeEarlyPct": 2.787,
      "slopeLatePct": 5.51,
      "totalReturn": 67.7
    },
    {
      "ticker": "323410.KS",
      "trend": "sideways",
      "slopePct": -1.388,
      "r2": 0.266,
      "slopeEarlyPct": -4.465,
      "slopeLatePct": -4.032,
      "totalReturn": -23.2
    },
    {
      "ticker": "000155.KS",
      "trend": "bullish",
      "slopePct": 4.822,
      "r2": 0.682,
      "slopeEarlyPct": 4.845,
      "slopeLatePct": 3.589,
      "totalReturn": 60.7
    },
    {
      "ticker": "047050.KS",
      "trend": "bullish",
      "slopePct": 3.692,
      "r2": 0.504,
      "slopeEarlyPct": 2.664,
      "slopeLatePct": -4.967,
      "totalReturn": 17.7
    },
    {
      "ticker": "443060.KS",
      "trend": "recovering",
      "slopePct": 0.527,
      "r2": 0.029,
      "slopeEarlyPct": -1.513,
      "slopeLatePct": 5.57,
      "totalReturn": 8
    },
    {
      "ticker": "071055.KS",
      "trend": "bullish",
      "slopePct": 5.853,
      "r2": 0.873,
      "slopeEarlyPct": 7.45,
      "slopeLatePct": -0.359,
      "totalReturn": 87.6
    },
    {
      "ticker": "039490.KS",
      "trend": "bullish",
      "slopePct": 5.705,
      "r2": 0.641,
      "slopeEarlyPct": 9.212,
      "slopeLatePct": -6.073,
      "totalReturn": 59
    },
    {
      "ticker": "028050.KS",
      "trend": "bullish",
      "slopePct": 7.16,
      "r2": 0.726,
      "slopeEarlyPct": 1.678,
      "slopeLatePct": 9.075,
      "totalReturn": 118.8
    },
    {
      "ticker": "003490.KS",
      "trend": "sideways",
      "slopePct": 1.067,
      "r2": 0.301,
      "slopeEarlyPct": -0.482,
      "slopeLatePct": -1.231,
      "totalReturn": 8.7
    },
    {
      "ticker": "454910.KS",
      "trend": "bullish",
      "slopePct": 6.241,
      "r2": 0.748,
      "slopeEarlyPct": 7.605,
      "slopeLatePct": 8.711,
      "totalReturn": 112.3
    },
    {
      "ticker": "047040.KS",
      "trend": "bullish",
      "slopePct": 20.057,
      "r2": 0.63,
      "slopeEarlyPct": 1.659,
      "slopeLatePct": 15.588,
      "totalReturn": 420.3
    },
    {
      "ticker": "352820.KS",
      "trend": "sideways",
      "slopePct": -1.159,
      "r2": 0.062,
      "slopeEarlyPct": 3.553,
      "slopeLatePct": -15.772,
      "totalReturn": -32.2
    },
    {
      "ticker": "007660.KS",
      "trend": "bullish",
      "slopePct": 5.962,
      "r2": 0.585,
      "slopeEarlyPct": 12.73,
      "slopeLatePct": 1.422,
      "totalReturn": 131.2
    },
    {
      "ticker": "00680K.KS",
      "trend": "bullish",
      "slopePct": 7.332,
      "r2": 0.612,
      "slopeEarlyPct": 8.362,
      "slopeLatePct": -10.422,
      "totalReturn": 79.4
    },
    {
      "ticker": "005830.KS",
      "trend": "bullish",
      "slopePct": 2.087,
      "r2": 0.387,
      "slopeEarlyPct": 1.062,
      "slopeLatePct": -6.381,
      "totalReturn": 15.5
    },
    {
      "ticker": "003230.KS",
      "trend": "bearish",
      "slopePct": -2.174,
      "r2": 0.613,
      "slopeEarlyPct": -2.655,
      "slopeLatePct": -1.618,
      "totalReturn": -19.7
    },
    {
      "ticker": "161390.KS",
      "trend": "bullish",
      "slopePct": 4.599,
      "r2": 0.687,
      "slopeEarlyPct": 7.465,
      "slopeLatePct": 0.421,
      "totalReturn": 70.8
    },
    {
      "ticker": "353200.KS",
      "trend": "bullish",
      "slopePct": 17.801,
      "r2": 0.787,
      "slopeEarlyPct": 17.113,
      "slopeLatePct": 24.672,
      "totalReturn": 779.9
    },
    {
      "ticker": "180640.KS",
      "trend": "sideways",
      "slopePct": 0.599,
      "r2": 0.036,
      "slopeEarlyPct": 0.139,
      "slopeLatePct": -6.671,
      "totalReturn": -2.7
    },
    {
      "ticker": "034220.KS",
      "trend": "sideways",
      "slopePct": 2.264,
      "r2": 0.298,
      "slopeEarlyPct": 2.528,
      "slopeLatePct": 5.076,
      "totalReturn": 69.8
    },
    {
      "ticker": "001440.KS",
      "trend": "bullish",
      "slopePct": 9.952,
      "r2": 0.733,
      "slopeEarlyPct": 8.727,
      "slopeLatePct": 6.519,
      "totalReturn": 131.7
    },
    {
      "ticker": "090430.KS",
      "trend": "sideways",
      "slopePct": -0.399,
      "r2": 0.027,
      "slopeEarlyPct": -0.475,
      "slopeLatePct": -8.5,
      "totalReturn": -21.4
    },
    {
      "ticker": "267270.KS",
      "trend": "bullish",
      "slopePct": 6.213,
      "r2": 0.766,
      "slopeEarlyPct": 3.568,
      "slopeLatePct": 2.697,
      "totalReturn": 94.3
    },
    {
      "ticker": "011790.KS",
      "trend": "sideways",
      "slopePct": 1.997,
      "r2": 0.279,
      "slopeEarlyPct": 1.572,
      "slopeLatePct": 9.376,
      "totalReturn": 29.1
    },
    {
      "ticker": "078930.KS",
      "trend": "bullish",
      "slopePct": 4.901,
      "r2": 0.836,
      "slopeEarlyPct": 5.12,
      "slopeLatePct": 2.701,
      "totalReturn": 58.8
    },
    {
      "ticker": "000990.KS",
      "trend": "bullish",
      "slopePct": 12.633,
      "r2": 0.794,
      "slopeEarlyPct": 11.2,
      "slopeLatePct": 19.017,
      "totalReturn": 271.4
    },
    {
      "ticker": "326030.KS",
      "trend": "sideways",
      "slopePct": -0.498,
      "r2": 0.017,
      "slopeEarlyPct": 4.814,
      "slopeLatePct": -6.957,
      "totalReturn": -4.2
    },
    {
      "ticker": "000250.KQ",
      "trend": "sideways",
      "slopePct": 8.817,
      "r2": 0.285,
      "slopeEarlyPct": 12.63,
      "slopeLatePct": -28.809,
      "totalReturn": 98.2
    },
    {
      "ticker": "062040.KS",
      "trend": "bullish",
      "slopePct": 7.531,
      "r2": 0.706,
      "slopeEarlyPct": 5.796,
      "slopeLatePct": 10.656,
      "totalReturn": 149.2
    },
    {
      "ticker": "032640.KS",
      "trend": "bullish",
      "slopePct": 0.775,
      "r2": 0.507,
      "slopeEarlyPct": 1.02,
      "slopeLatePct": -1.159,
      "totalReturn": 7.1
    },
    {
      "ticker": "021240.KS",
      "trend": "recovering",
      "slopePct": -1.689,
      "r2": 0.369,
      "slopeEarlyPct": -3.382,
      "slopeLatePct": 4.995,
      "totalReturn": -2.7
    },
    {
      "ticker": "009830.KS",
      "trend": "bullish",
      "slopePct": 4.038,
      "r2": 0.384,
      "slopeEarlyPct": -1.899,
      "slopeLatePct": -5.54,
      "totalReturn": 21.5
    },
    {
      "ticker": "336260.KS",
      "trend": "bullish",
      "slopePct": 11.012,
      "r2": 0.653,
      "slopeEarlyPct": 5.215,
      "slopeLatePct": 23.56,
      "totalReturn": 272.4
    },
    {
      "ticker": "240810.KQ",
      "trend": "bullish",
      "slopePct": 11.416,
      "r2": 0.881,
      "slopeEarlyPct": 18.236,
      "slopeLatePct": 1.026,
      "totalReturn": 401.7
    },
    {
      "ticker": "241560.KS",
      "trend": "bullish",
      "slopePct": 1.685,
      "r2": 0.526,
      "slopeEarlyPct": 0.543,
      "slopeLatePct": 1.449,
      "totalReturn": 13.1
    },
    {
      "ticker": "128940.KS",
      "trend": "bullish",
      "slopePct": 4.767,
      "r2": 0.698,
      "slopeEarlyPct": 8.632,
      "slopeLatePct": -4.348,
      "totalReturn": 72.7
    },
    {
      "ticker": "001040.KS",
      "trend": "sideways",
      "slopePct": 1.759,
      "r2": 0.276,
      "slopeEarlyPct": 3.541,
      "slopeLatePct": -4.946,
      "totalReturn": 14.5
    },
    {
      "ticker": "377300.KS",
      "trend": "bearish",
      "slopePct": -2.583,
      "r2": 0.369,
      "slopeEarlyPct": -4.067,
      "slopeLatePct": -8.661,
      "totalReturn": -41
    },
    {
      "ticker": "000100.KS",
      "trend": "bearish",
      "slopePct": -2.681,
      "r2": 0.603,
      "slopeEarlyPct": 0.234,
      "slopeLatePct": -8.19,
      "totalReturn": -25.6
    },
    {
      "ticker": "004170.KS",
      "trend": "bullish",
      "slopePct": 11.476,
      "r2": 0.802,
      "slopeEarlyPct": 8.193,
      "slopeLatePct": 17.347,
      "totalReturn": 245
    },
    {
      "ticker": "010060.KS",
      "trend": "bullish",
      "slopePct": 13.771,
      "r2": 0.722,
      "slopeEarlyPct": 5.786,
      "slopeLatePct": 16.769,
      "totalReturn": 310
    },
    {
      "ticker": "00104K.KS",
      "trend": "bullish",
      "slopePct": 2.401,
      "r2": 0.534,
      "slopeEarlyPct": 4.176,
      "slopeLatePct": -3.1,
      "totalReturn": 27.2
    },
    {
      "ticker": "036570.KS",
      "trend": "bullish",
      "slopePct": 3.038,
      "r2": 0.738,
      "slopeEarlyPct": 1.472,
      "slopeLatePct": 6.421,
      "totalReturn": 36.3
    },
    {
      "ticker": "138930.KS",
      "trend": "bullish",
      "slopePct": 2.779,
      "r2": 0.667,
      "slopeEarlyPct": 2.977,
      "slopeLatePct": -3.559,
      "totalReturn": 38.5
    },
    {
      "ticker": "271560.KS",
      "trend": "bullish",
      "slopePct": 2.484,
      "r2": 0.636,
      "slopeEarlyPct": 0.24,
      "slopeLatePct": 0,
      "totalReturn": 21.9
    },
    {
      "ticker": "000500.KS",
      "trend": "bullish",
      "slopePct": 15.785,
      "r2": 0.674,
      "slopeEarlyPct": 5.256,
      "slopeLatePct": 27.647,
      "totalReturn": 363
    },
    {
      "ticker": "029780.KS",
      "trend": "sideways",
      "slopePct": 0.039,
      "r2": 0,
      "slopeEarlyPct": 2.107,
      "slopeLatePct": -7.828,
      "totalReturn": -6.9
    },
    {
      "ticker": "023530.KS",
      "trend": "bullish",
      "slopePct": 8.351,
      "r2": 0.766,
      "slopeEarlyPct": 1.366,
      "slopeLatePct": 12.658,
      "totalReturn": 133.2
    },
    {
      "ticker": "052690.KS",
      "trend": "bullish",
      "slopePct": 5.114,
      "r2": 0.486,
      "slopeEarlyPct": 2.36,
      "slopeLatePct": -7.25,
      "totalReturn": 22.1
    },
    {
      "ticker": "018880.KS",
      "trend": "bullish",
      "slopePct": 3.701,
      "r2": 0.488,
      "slopeEarlyPct": 0.534,
      "slopeLatePct": 4.36,
      "totalReturn": 51.5
    },
    {
      "ticker": "175330.KS",
      "trend": "bullish",
      "slopePct": 1.979,
      "r2": 0.399,
      "slopeEarlyPct": 2.35,
      "slopeLatePct": -6.431,
      "totalReturn": 25.3
    },
    {
      "ticker": "004020.KS",
      "trend": "sideways",
      "slopePct": 2.042,
      "r2": 0.294,
      "slopeEarlyPct": -0.629,
      "slopeLatePct": -3.698,
      "totalReturn": 22.1
    },
    {
      "ticker": "082740.KS",
      "trend": "bullish",
      "slopePct": 5.427,
      "r2": 0.515,
      "slopeEarlyPct": 5.855,
      "slopeLatePct": 4.125,
      "totalReturn": 97.9
    },
    {
      "ticker": "022100.KS",
      "trend": "bullish",
      "slopePct": 3.643,
      "r2": 0.469,
      "slopeEarlyPct": 6.557,
      "slopeLatePct": -5.203,
      "totalReturn": 24.5
    },
    {
      "ticker": "051900.KS",
      "trend": "bearish",
      "slopePct": -2.213,
      "r2": 0.894,
      "slopeEarlyPct": -3.086,
      "slopeLatePct": -1.484,
      "totalReturn": -22.4
    },
    {
      "ticker": "095340.KQ",
      "trend": "bullish",
      "slopePct": 12.146,
      "r2": 0.866,
      "slopeEarlyPct": 14.121,
      "slopeLatePct": -0.564,
      "totalReturn": 237.8
    },
    {
      "ticker": "002380.KS",
      "trend": "bullish",
      "slopePct": 4.394,
      "r2": 0.715,
      "slopeEarlyPct": 4.729,
      "slopeLatePct": -2.698,
      "totalReturn": 73.7
    },
    {
      "ticker": "450080.KS",
      "trend": "bullish",
      "slopePct": 2.962,
      "r2": 0.431,
      "slopeEarlyPct": 4.346,
      "slopeLatePct": -5.706,
      "totalReturn": 21.4
    },
    {
      "ticker": "00088K.KS",
      "trend": "sideways",
      "slopePct": 2.181,
      "r2": 0.337,
      "slopeEarlyPct": 1.072,
      "slopeLatePct": -4.054,
      "totalReturn": 9.1
    },
    {
      "ticker": "103590.KS",
      "trend": "bullish",
      "slopePct": 8.584,
      "r2": 0.706,
      "slopeEarlyPct": 7.784,
      "slopeLatePct": 0.746,
      "totalReturn": 97.1
    },
    {
      "ticker": "489790.KS",
      "trend": "bullish",
      "slopePct": 3.822,
      "r2": 0.42,
      "slopeEarlyPct": -0.815,
      "slopeLatePct": -4.158,
      "totalReturn": 42.4
    },
    {
      "ticker": "088350.KS",
      "trend": "bullish",
      "slopePct": 4.466,
      "r2": 0.676,
      "slopeEarlyPct": -0.105,
      "slopeLatePct": 0.23,
      "totalReturn": 45.2
    },
    {
      "ticker": "251270.KS",
      "trend": "bearish",
      "slopePct": -2.985,
      "r2": 0.857,
      "slopeEarlyPct": -3.154,
      "slopeLatePct": -5.912,
      "totalReturn": -32.3
    },
    {
      "ticker": "111770.KS",
      "trend": "bullish",
      "slopePct": 3.007,
      "r2": 0.456,
      "slopeEarlyPct": 6.397,
      "slopeLatePct": -3.975,
      "totalReturn": 26.3
    },
    {
      "ticker": "012510.KS",
      "trend": "bullish",
      "slopePct": 4.906,
      "r2": 0.905,
      "slopeEarlyPct": 4.541,
      "slopeLatePct": 0.343,
      "totalReturn": 77.8
    },
    {
      "ticker": "011780.KS",
      "trend": "bullish",
      "slopePct": 1.889,
      "r2": 0.369,
      "slopeEarlyPct": 2.497,
      "slopeLatePct": -2.82,
      "totalReturn": 13.2
    },
    {
      "ticker": "011170.KS",
      "trend": "bullish",
      "slopePct": 3.459,
      "r2": 0.496,
      "slopeEarlyPct": 3.793,
      "slopeLatePct": -4.091,
      "totalReturn": 31.8
    },
    {
      "ticker": "007810.KS",
      "trend": "bullish",
      "slopePct": 18.524,
      "r2": 0.922,
      "slopeEarlyPct": 27.962,
      "slopeLatePct": 18.197,
      "totalReturn": 954.7
    },
    {
      "ticker": "005850.KS",
      "trend": "bullish",
      "slopePct": 7.833,
      "r2": 0.848,
      "slopeEarlyPct": 7.418,
      "slopeLatePct": 1.828,
      "totalReturn": 123
    },
    {
      "ticker": "097950.KS",
      "trend": "bearish",
      "slopePct": -1.332,
      "r2": 0.426,
      "slopeEarlyPct": -2.749,
      "slopeLatePct": -1.969,
      "totalReturn": -19.7
    },
    {
      "ticker": "302440.KS",
      "trend": "sideways",
      "slopePct": -1.304,
      "r2": 0.3,
      "slopeEarlyPct": 1.445,
      "slopeLatePct": -4.381,
      "totalReturn": -16.3
    },
    {
      "ticker": "069960.KS",
      "trend": "bullish",
      "slopePct": 4.647,
      "r2": 0.662,
      "slopeEarlyPct": 3.721,
      "slopeLatePct": 9.343,
      "totalReturn": 93.8
    },
    {
      "ticker": "375500.KS",
      "trend": "recovering",
      "slopePct": 5.874,
      "r2": 0.488,
      "slopeEarlyPct": -2.364,
      "slopeLatePct": 7.022,
      "totalReturn": 38.8
    },
    {
      "ticker": "036460.KS",
      "trend": "bearish",
      "slopePct": -1.343,
      "r2": 0.568,
      "slopeEarlyPct": -0.593,
      "slopeLatePct": -3.412,
      "totalReturn": -16.9
    },
    {
      "ticker": "035250.KS",
      "trend": "bearish",
      "slopePct": -1.309,
      "r2": 0.462,
      "slopeEarlyPct": -0.42,
      "slopeLatePct": -5.911,
      "totalReturn": -17.7
    },
    {
      "ticker": "031210.KS",
      "trend": "sideways",
      "slopePct": 0.581,
      "r2": 0.048,
      "slopeEarlyPct": 2.778,
      "slopeLatePct": -8.036,
      "totalReturn": -0.5
    },
    {
      "ticker": "004800.KS",
      "trend": "bullish",
      "slopePct": 8.003,
      "r2": 0.788,
      "slopeEarlyPct": 9.386,
      "slopeLatePct": 4.973,
      "totalReturn": 134.6
    },
    {
      "ticker": "009420.KS",
      "trend": "bullish",
      "slopePct": 6.891,
      "r2": 0.845,
      "slopeEarlyPct": 10.673,
      "slopeLatePct": -0.07,
      "totalReturn": 138.8
    },
    {
      "ticker": "020150.KS",
      "trend": "bullish",
      "slopePct": 8.853,
      "r2": 0.818,
      "slopeEarlyPct": 7.838,
      "slopeLatePct": 6.794,
      "totalReturn": 152.5
    },
    {
      "ticker": "014680.KS",
      "trend": "bullish",
      "slopePct": 4.038,
      "r2": 0.614,
      "slopeEarlyPct": 6.688,
      "slopeLatePct": -5.189,
      "totalReturn": 49.4
    },
    {
      "ticker": "001450.KS",
      "trend": "bullish",
      "slopePct": 2.297,
      "r2": 0.728,
      "slopeEarlyPct": 1.692,
      "slopeLatePct": 2.209,
      "totalReturn": 35.3
    },
    {
      "ticker": "139130.KS",
      "trend": "bullish",
      "slopePct": 3.189,
      "r2": 0.809,
      "slopeEarlyPct": 2.553,
      "slopeLatePct": -0.42,
      "totalReturn": 40.8
    },
    {
      "ticker": "005290.KQ",
      "trend": "bullish",
      "slopePct": 5.093,
      "r2": 0.728,
      "slopeEarlyPct": 6.454,
      "slopeLatePct": 1.969,
      "totalReturn": 67.9
    },
    {
      "ticker": "017800.KS",
      "trend": "sideways",
      "slopePct": 0.393,
      "r2": 0.028,
      "slopeEarlyPct": 1.336,
      "slopeLatePct": -5.366,
      "totalReturn": -9.9
    },
    {
      "ticker": "383220.KS",
      "trend": "recovering",
      "slopePct": -0.001,
      "r2": 0,
      "slopeEarlyPct": -0.54,
      "slopeLatePct": 2.547,
      "totalReturn": -6.7
    },
    {
      "ticker": "028670.KS",
      "trend": "bullish",
      "slopePct": 3.481,
      "r2": 0.721,
      "slopeEarlyPct": 1.403,
      "slopeLatePct": 0.522,
      "totalReturn": 37.8
    },
    {
      "ticker": "131970.KQ",
      "trend": "bullish",
      "slopePct": 14.381,
      "r2": 0.856,
      "slopeEarlyPct": 11.67,
      "slopeLatePct": 16.124,
      "totalReturn": 417.6
    },
    {
      "ticker": "204320.KS",
      "trend": "bullish",
      "slopePct": 5.302,
      "r2": 0.681,
      "slopeEarlyPct": 10.331,
      "slopeLatePct": -0.376,
      "totalReturn": 68
    },
    {
      "ticker": "457190.KS",
      "trend": "bullish",
      "slopePct": 8.416,
      "r2": 0.672,
      "slopeEarlyPct": 11.715,
      "slopeLatePct": -5.16,
      "totalReturn": 101.9
    },
    {
      "ticker": "010170.KQ",
      "trend": "bullish",
      "slopePct": 25.203,
      "r2": 0.704,
      "slopeEarlyPct": 17.807,
      "slopeLatePct": 31.891,
      "totalReturn": 1781.4
    },
    {
      "ticker": "012750.KS",
      "trend": "sideways",
      "slopePct": 0.424,
      "r2": 0.037,
      "slopeEarlyPct": 0.659,
      "slopeLatePct": -5.69,
      "totalReturn": 7.3
    },
    {
      "ticker": "085620.KS",
      "trend": "bullish",
      "slopePct": 8.895,
      "r2": 0.884,
      "slopeEarlyPct": 5.677,
      "slopeLatePct": 5.79,
      "totalReturn": 194.1
    },
    {
      "ticker": "139480.KS",
      "trend": "sideways",
      "slopePct": 1.816,
      "r2": 0.297,
      "slopeEarlyPct": 0.236,
      "slopeLatePct": -4.268,
      "totalReturn": 4.4
    },
    {
      "ticker": "006360.KS",
      "trend": "recovering",
      "slopePct": 4.85,
      "r2": 0.523,
      "slopeEarlyPct": -0.612,
      "slopeLatePct": 5.565,
      "totalReturn": 33.5
    },
    {
      "ticker": "000240.KS",
      "trend": "sideways",
      "slopePct": 1.141,
      "r2": 0.135,
      "slopeEarlyPct": 3.918,
      "slopeLatePct": -4.909,
      "totalReturn": 29.2
    },
    {
      "ticker": "001740.KS",
      "trend": "bullish",
      "slopePct": 7.809,
      "r2": 0.55,
      "slopeEarlyPct": 2.116,
      "slopeLatePct": 21.513,
      "totalReturn": 143.3
    },
    {
      "ticker": "026960.KS",
      "trend": "bearish",
      "slopePct": -1.147,
      "r2": 0.607,
      "slopeEarlyPct": -1.344,
      "slopeLatePct": -4.009,
      "totalReturn": -16.7
    },
    {
      "ticker": "003690.KS",
      "trend": "bullish",
      "slopePct": 2.091,
      "r2": 0.751,
      "slopeEarlyPct": 1.844,
      "slopeLatePct": -0.877,
      "totalReturn": 27.4
    },
    {
      "ticker": "439260.KS",
      "trend": "sideways",
      "slopePct": -1.033,
      "r2": 0.045,
      "slopeEarlyPct": 0.509,
      "slopeLatePct": -13.861,
      "totalReturn": -30.2
    },
    {
      "ticker": "004370.KS",
      "trend": "sideways",
      "slopePct": -0.679,
      "r2": 0.156,
      "slopeEarlyPct": 1.266,
      "slopeLatePct": -2.457,
      "totalReturn": -5
    },
    {
      "ticker": "120110.KS",
      "trend": "bullish",
      "slopePct": 7.181,
      "r2": 0.662,
      "slopeEarlyPct": 3.107,
      "slopeLatePct": -0.618,
      "totalReturn": 49.6
    },
    {
      "ticker": "282330.KS",
      "trend": "bullish",
      "slopePct": 1.45,
      "r2": 0.368,
      "slopeEarlyPct": -0.744,
      "slopeLatePct": -0.454,
      "totalReturn": 6.9
    },
    {
      "ticker": "071970.KS",
      "trend": "sideways",
      "slopePct": 0.818,
      "r2": 0.027,
      "slopeEarlyPct": 5.3,
      "slopeLatePct": -5.092,
      "totalReturn": 30.8
    },
    {
      "ticker": "051600.KS",
      "trend": "sideways",
      "slopePct": 0.222,
      "r2": 0.009,
      "slopeEarlyPct": -0.69,
      "slopeLatePct": -5.584,
      "totalReturn": -19.1
    },
    {
      "ticker": "007390.KQ",
      "trend": "recovering",
      "slopePct": -0.459,
      "r2": 0.005,
      "slopeEarlyPct": -4.286,
      "slopeLatePct": 15.53,
      "totalReturn": 21.9
    },
    {
      "ticker": "009970.KS",
      "trend": "bullish",
      "slopePct": 4.123,
      "r2": 0.578,
      "slopeEarlyPct": 6.305,
      "slopeLatePct": -7.329,
      "totalReturn": 33.7
    },
    {
      "ticker": "008930.KS",
      "trend": "bearish",
      "slopePct": -2.506,
      "r2": 0.552,
      "slopeEarlyPct": -2.706,
      "slopeLatePct": -8.045,
      "totalReturn": -29.4
    },
    {
      "ticker": "007340.KS",
      "trend": "recovering",
      "slopePct": 5.995,
      "r2": 0.612,
      "slopeEarlyPct": -0.453,
      "slopeLatePct": 8.68,
      "totalReturn": 85.8
    },
    {
      "ticker": "011210.KS",
      "trend": "bullish",
      "slopePct": 5.782,
      "r2": 0.734,
      "slopeEarlyPct": 9.082,
      "slopeLatePct": -3.321,
      "totalReturn": 74.7
    },
    {
      "ticker": "008770.KS",
      "trend": "recovering",
      "slopePct": 1.253,
      "r2": 0.168,
      "slopeEarlyPct": -1.419,
      "slopeLatePct": 4.816,
      "totalReturn": 7
    },
    {
      "ticker": "081660.KS",
      "trend": "sideways",
      "slopePct": 0.833,
      "r2": 0.106,
      "slopeEarlyPct": 3.362,
      "slopeLatePct": -5.407,
      "totalReturn": 10.6
    },
    {
      "ticker": "003540.KS",
      "trend": "bullish",
      "slopePct": 2.899,
      "r2": 0.361,
      "slopeEarlyPct": 2.432,
      "slopeLatePct": -9.614,
      "totalReturn": 23
    },
    {
      "ticker": "007070.KS",
      "trend": "bullish",
      "slopePct": 3.901,
      "r2": 0.895,
      "slopeEarlyPct": 4.818,
      "slopeLatePct": 3.271,
      "totalReturn": 44.1
    },
    {
      "ticker": "018670.KS",
      "trend": "sideways",
      "slopePct": -0.397,
      "r2": 0.036,
      "slopeEarlyPct": -1.93,
      "slopeLatePct": -2.201,
      "totalReturn": -14.1
    },
    {
      "ticker": "103140.KS",
      "trend": "bearish",
      "slopePct": -4.434,
      "r2": 0.64,
      "slopeEarlyPct": -3.183,
      "slopeLatePct": -10.293,
      "totalReturn": -43.8
    },
    {
      "ticker": "002790.KS",
      "trend": "sideways",
      "slopePct": -1.627,
      "r2": 0.348,
      "slopeEarlyPct": -1.679,
      "slopeLatePct": -8.899,
      "totalReturn": -30.7
    },
    {
      "ticker": "161890.KS",
      "trend": "recovering",
      "slopePct": -0.81,
      "r2": 0.052,
      "slopeEarlyPct": -6.369,
      "slopeLatePct": 2.915,
      "totalReturn": -16.3
    },
    {
      "ticker": "005440.KS",
      "trend": "bullish",
      "slopePct": 5.699,
      "r2": 0.596,
      "slopeEarlyPct": 0.263,
      "slopeLatePct": -4.782,
      "totalReturn": 41.1
    },
    {
      "ticker": "097230.KS",
      "trend": "sideways",
      "slopePct": 4.162,
      "r2": 0.275,
      "slopeEarlyPct": 11.227,
      "slopeLatePct": -3.507,
      "totalReturn": 173.6
    },
    {
      "ticker": "192820.KS",
      "trend": "bearish",
      "slopePct": -3.094,
      "r2": 0.511,
      "slopeEarlyPct": -6.411,
      "slopeLatePct": -3.79,
      "totalReturn": -40.6
    },
    {
      "ticker": "030000.KS",
      "trend": "sideways",
      "slopePct": -0.492,
      "r2": 0.085,
      "slopeEarlyPct": 1.578,
      "slopeLatePct": -4.006,
      "totalReturn": -8.8
    },
    {
      "ticker": "030530.KQ",
      "trend": "bullish",
      "slopePct": 8.463,
      "r2": 0.372,
      "slopeEarlyPct": 28.475,
      "slopeLatePct": -7.236,
      "totalReturn": 338.8
    },
    {
      "ticker": "229640.KS",
      "trend": "bullish",
      "slopePct": 6.143,
      "r2": 0.492,
      "slopeEarlyPct": 1.094,
      "slopeLatePct": 9.36,
      "totalReturn": 74.2
    },
    {
      "ticker": "112610.KS",
      "trend": "sideways",
      "slopePct": 2.079,
      "r2": 0.183,
      "slopeEarlyPct": -1.811,
      "slopeLatePct": -5.756,
      "totalReturn": -6.5
    },
    {
      "ticker": "004990.KS",
      "trend": "sideways",
      "slopePct": -0.213,
      "r2": 0.007,
      "slopeEarlyPct": 0.489,
      "slopeLatePct": -7.88,
      "totalReturn": -9
    },
    {
      "ticker": "322000.KS",
      "trend": "bullish",
      "slopePct": 14.683,
      "r2": 0.704,
      "slopeEarlyPct": 3.91,
      "slopeLatePct": 9.186,
      "totalReturn": 265.2
    },
    {
      "ticker": "462870.KS",
      "trend": "bearish",
      "slopePct": -3.836,
      "r2": 0.917,
      "slopeEarlyPct": -4.244,
      "slopeLatePct": -2.292,
      "totalReturn": -37.5
    }
  ]
}